patchioner/__init__.py
patchioner/bbox_utils.py
patchioner/dataset.py
patchioner/datasetMix.py
patchioner/dino_extraction.py
patchioner/dinotxt_utils.py
patchioner/embedding_utils.py
patchioner/hf_utils.py
patchioner/model.py
patchioner/INViTE/__init__.py
patchioner/INViTE/loader.py
patchioner/alphaclip/__init__.py
patchioner/alphaclip/alpha_mask_utils.py
patchioner/alphaclip/alphaclip_loader.py
patchioner/alphaclip/example.py
patchioner/alphaclip/setup.py
patchioner/alphaclip/test_installation.py
patchioner/clip/bpe_simple_vocab_16e6.txt.gz
patchioner/clip/simple_tokenizer.py
patchioner/clipcap/__init__.py
patchioner/clipcap/clipcapTraining.py
patchioner/clipcap/clipcap_dino_parse_coco.py
patchioner/clipcap/clipcap_parse_coco.py
patchioner/clipcap/entrypoint.py
patchioner/clipcap/predict.py
patchioner/decap/__init__.py
patchioner/decap/decap.py
patchioner/decap/decoderTraining.py
patchioner/decap/decoder_config.pkl
patchioner/decap/im2txtprojection/__init__.py
patchioner/decap/im2txtprojection/im2txtprojection.py
patchioner/denseclip/__init__.py
patchioner/denseclip/loader.py
patchioner/meacap/__init__.py
patchioner/meacap/args.py
patchioner/meacap/entrypoint.py
patchioner/meacap/prepare_embeddings.py
patchioner/meacap/talk2dino.py
patchioner/meacap/viecap_inference.py
patchioner/meacap/models/__init__.py
patchioner/meacap/models/clip_utils.py
patchioner/meacap/utils/__init__.py
patchioner/meacap/utils/detect_utils.py
patchioner/meacap/utils/log.py
patchioner/meacap/utils/parse_tool.py
patchioner/meacap/utils/some_utils.py
patchioner/proxyclip/__init__.py
patchioner/proxyclip/proxyclip.py
patchioner/proxyclip/open_clip_proxy/__init__.py
patchioner/proxyclip/open_clip_proxy/big_vision.py
patchioner/proxyclip/open_clip_proxy/bpe_simple_vocab_16e6.txt.gz
patchioner/proxyclip/open_clip_proxy/coca_model.py
patchioner/proxyclip/open_clip_proxy/constants.py
patchioner/proxyclip/open_clip_proxy/factory.py
patchioner/proxyclip/open_clip_proxy/hf_configs.py
patchioner-0.1.1.dist-info/METADATA
patchioner-0.1.1.dist-info/WHEEL
patchioner-0.1.1.dist-info/top_level.txt
patchioner-0.1.1.dist-info/RECORD
