Metadata-Version: 2.1
Name: patchioner
Version: 0.1.1
Summary: Patch-ioner: A Unified Zero-Shot Captioning Framework
Author-email: Lorenzo Bianchi <lorenzo.bianchi@isti.cnr.it>, Giacomo Pacini <giacomo.pacini@isti.cnr.it>
Requires-Python: >=3.8
Requires-Dist: torch
Requires-Dist: transformers ==4.46.3
Requires-Dist: ipykernel
Requires-Dist: tqdm
Requires-Dist: python-dotenv
Requires-Dist: h5py
Requires-Dist: scikit-learn
Requires-Dist: plotly
Requires-Dist: pandas
Requires-Dist: matplotlib
Requires-Dist: pycocotools
Requires-Dist: nbformat
Requires-Dist: speaksee
Requires-Dist: munkres
Requires-Dist: open-clip-torch
Requires-Dist: sentence-transformers
Requires-Dist: nltk
